make_dicom/__init__.py
make_dicom/config.py
make_dicom/dicom_maker.py
make_dicom/main.py
make_dicom/data/__init__.py
make_dicom/data/modality_configs.py
make_dicom/generators/__init__.py
make_dicom/generators/dicom_generator.py
make_dicom/generators/institution_generator.py
make_dicom/generators/patient_generator.py
make_dicom/generators/study_generator.py
make_dicom/utils/__init__.py
make_dicom/utils/template_generator.py
make_dicom/utils/uid_generator.py
dicom_maker-1.0.6.dist-info/METADATA
dicom_maker-1.0.6.dist-info/WHEEL
dicom_maker-1.0.6.dist-info/entry_points.txt
dicom_maker-1.0.6.dist-info/top_level.txt
dicom_maker-1.0.6.dist-info/RECORD
