Metadata-Version: 2.4
Name: dicom-maker
Version: 1.0.6
Summary: Enhanced DICOM Generator for creating sample DICOM studies
Home-page: https://github.com/aurabox/dicom-maker
Author: Aurabox
Author-email: hello@aurabox.cloud
Classifier: Programming Language :: Python :: 3
Classifier: License :: OSI Approved :: MIT License
Classifier: Operating System :: OS Independent
Classifier: Topic :: Scientific/Engineering :: Medical Science Apps.
Classifier: Intended Audience :: Healthcare Industry
Classifier: Intended Audience :: Science/Research
Requires-Python: >=3.6
Requires-Dist: pathlib>=1.0.1
Dynamic: author
Dynamic: author-email
Dynamic: classifier
Dynamic: description
Dynamic: description-content-type
Dynamic: home-page
Dynamic: requires-dist
Dynamic: requires-python
Dynamic: summary
